dexpresso/Client.py
dexpresso/Configs.py
dexpresso/EasyClient.py
dexpresso/GeneralClient.py
dexpresso/OfflineSigner.py
dexpresso/Web3Client.py
dexpresso/Web3EasyClient.py
dexpresso/Web3OfflineSigner.py
dexpresso/ZkSyncOneEasyClient.py
dexpresso/__init__.py
examples/__init__.py
examples/submit_order.py
dexpresso-0.4.0.dist-info/LICENSE
dexpresso-0.4.0.dist-info/METADATA
dexpresso-0.4.0.dist-info/WHEEL
dexpresso-0.4.0.dist-info/top_level.txt
dexpresso-0.4.0.dist-info/RECORD
