Metadata-Version: 2.1
Name: dexpresso
Version: 0.4.0
Summary: A library for better and safer interactions with Dexpresso exchange
Author-email: "dexpresso.protocol" <dexpresso_dev@proton.me>
Project-URL: Homepage, https://github.com/dexpresso-protocol/sdk
Project-URL: Bug Tracker, https://github.com/dexpresso-protocol/sdk/issues
Classifier: Programming Language :: Python :: 3
Classifier: License :: OSI Approved :: MIT License
Classifier: Operating System :: OS Independent
Classifier: Development Status :: 5 - Production/Stable
Classifier: Intended Audience :: Developers
Classifier: Natural Language :: English
Classifier: Programming Language :: Python :: 3.7
Classifier: Programming Language :: Python :: 3.8
Classifier: Programming Language :: Python :: 3.9
Classifier: Programming Language :: Python :: 3.10
Requires-Python: >=3.7
License-File: LICENSE
Requires-Dist: web3 (>=5.31.1)
Requires-Dist: zksync-sdk (>=0.1.667)
Requires-Dist: hexbytes (>=0.3.0)
Requires-Dist: requests (>=2.28.1)
